aliyun/__init__.py
aliyun/api/__init__.py
aliyun/api/base.py
aliyun/api/rest/__init__.py
hifive/__init__.py
hifive/api/__init__.py
hifive/api/base.py
hifive/api/rest/AreaEnum.py
hifive/api/rest/EducationEnum.py
hifive/api/rest/GenderEnum.py
hifive/api/rest/HFBaseFavoriteRequest.py
hifive/api/rest/HFBaseHotRequest.py
hifive/api/rest/HFBaseLoginRequest.py
hifive/api/rest/HFBaseReportRequest.py
hifive/api/rest/HFBaseVisualRequest.py
hifive/api/rest/HFBaseWeatherRequest.py
hifive/api/rest/HFBitRateEnum.py
hifive/api/rest/HFChannelRequest.py
hifive/api/rest/HFChannelSheetRequest.py
hifive/api/rest/HFHQListenRequest.py
hifive/api/rest/HFHQListenSliceRequest.py
hifive/api/rest/HFMusicConfigRequest.py
hifive/api/rest/HFOrderAuthorizationRequest.py
hifive/api/rest/HFOrderDetailRequest.py
hifive/api/rest/HFOrderGroupRequest.py
hifive/api/rest/HFOrderGroupSheetRequest.py
hifive/api/rest/HFOrderListenMixedRequest.py
hifive/api/rest/HFOrderListenRequest.py
hifive/api/rest/HFOrderListenSliceRequest.py
hifive/api/rest/HFOrderMusicRequest.py
hifive/api/rest/HFOrderPublishRequest.py
hifive/api/rest/HFOrderRefundRequest.py
hifive/api/rest/HFOrderSearchMusicRequest.py
hifive/api/rest/HFOrderSheetMusicRequest.py
hifive/api/rest/HFOrderTagMusicRequest.py
hifive/api/rest/HFOrderTagRequest.py
hifive/api/rest/HFOrderTagSheetRequest.py
hifive/api/rest/HFSearchMusicRequest.py
hifive/api/rest/HFSheetMusicRequest.py
hifive/api/rest/HFSheetTagRequest.py
hifive/api/rest/HFTagSheetRequest.py
hifive/api/rest/HFTrafficDownloadRequest.py
hifive/api/rest/HFTrafficGroupRequest.py
hifive/api/rest/HFTrafficGroupSheetRequest.py
hifive/api/rest/HFTrafficListenMixedRequest.py
hifive/api/rest/HFTrafficListenRequest.py
hifive/api/rest/HFTrafficListenSliceRequest.py
hifive/api/rest/HFTrafficSearchMusicRequest.py
hifive/api/rest/HFTrafficSheetMusicRequest.py
hifive/api/rest/HFTrafficTagMusicRequest.py
hifive/api/rest/HFTrafficTagRequest.py
hifive/api/rest/HFTrafficTagSheetRequest.py
hifive_openapi_py-4.0.1.dist-info/LICENSE
hifive_openapi_py-4.0.1.dist-info/METADATA
hifive_openapi_py-4.0.1.dist-info/WHEEL
hifive_openapi_py-4.0.1.dist-info/top_level.txt
hifive_openapi_py-4.0.1.dist-info/RECORD
